{
    "ok": "Ok",
    "cancel": "Cancelar",
    "confirm": "Confirmar",
    "yes": "Si",
    "no": "No",
    "add": "Agregar",
    "done": "Listo",
    "toAttach": "Adjuntar",
    "attachments": "Adjuntos",
    "file": "Archivo",
    "toAttachDocumment": "Adjuntar Documentos",
    "edit": "Editar",
    "delete": "Eliminar",
    "select": "Seleccione",
    "camera": "Cámara",
    "gallery": "Galería de imágenes",
    "crop": "Recortar",
    "requiredField": "Requerido",
    "send": "Enviar",
    "phoneNumber": "Número de teléfono",
    "enterPhoneNumber": "Ingresa tu \nnúmero de \nteléfono",
    "dni": "Cédula de Identidad",
    "gender": "Sexo",
    "age": "Edad",
    "year": "Año",
    "address": "Dirección",
    "male": "Masculino",
    "female": "Femenino",
    "province": "Provincia",
    "institution": "Institución",
    "institutions": "Instituciones",
    "nationality": "Nacionalidad",
    "rightViolated": "Derecho vulnerado",
    "rightsVolated": "Derechos vulnerados",
    "enterCode": "Ingrese el código",
    "resendCode": "Reenviar código",
    "resendCodeIn": "Reenviar código en",
    "registerAccount": "Registrar tu cuenta",

    "name": "Nombre",
    "names": "Nombres",
    "fistName": "Primer nombre",
    "secondName": "Segundo nombre",
    "lastName": "Apellido",
    "lastNames": "Apellidos",
    "firstLastName": "Primer apellido",
    "secondLastName": "Segundo apellido",
    "nameAndLastNames": "Nombre y Apellidos",
    "bithDate": "Fecha de nacimiento",
    "date": "Fecha",
    "smsCodePlaholder": "123456",
    "location": "Ubicación",
    "menuTitle": "Contraloría General",
    "mapView": "Ver en mapa",
    "listView": "Ver en lista",
    "info": "Información",
    "error": "Error",
    "unassigned": "Sin asignar",
    "writeComment": "Escribe un comentario",
    "showMore": "Ver más",
    "showLess": "Ver menos",
    "viewAll": "Ver todos",
    "comments": "Comentarios",
    "detail": "Detalle",
    "description": "Descripción",
    "downloadAttachments": "Descargar Adjuntos",
    "lastUpdated": "Ultima actualización",
    "managedBy": "Gestionado por",
    "search": "Buscar",
    "typeReport": "Tipo de denuncia",
    "reportSummary": "Resumen de la denuncia",
    "preview": "Atrás",
    "sendForm": "Enviar formulario",
    "informer": "Denunciante",
    "denounced": "Denunciado",
    "denounceds": "Denunciados",
    "denouncedData": "Datos del Denunciado",
    "optionalData":"Datos opcionales",
    "complaintDetail":"Detalles d ela denuncia",
    "gotoProfile": "Ir a perfil",
    "coordinatesOutOfZone": "Coordenadas fuera de zona",
    "aLocationInMap": "una localización en el mapa",
    "locationReportTitle": "Lugar donde ocurren los hechos de la denuncia.",
    "tapToSelect": "Toque para seleccionar",

    "loginTipMessage": "Te vamos a enviar un código de verificación a tu celular para iniciar sesión",
    "notConnectionMessage": "Ups!, al parecer tienes problemas con tu conexión a internet, porfavor verifica tu conexión.",
    "unexpectedErrorMessage": "Ocurrió un error inesperado",
    "invalidNameMessage": "Escribe al menos un nombre y un apellido. Deben tener mínimo dos caracteres cada uno, sin números o caracteres especiales.",
    "invalidPhoneNumberMessage": "Introduzca un número valido",
    "invaliEmailMessage": "Introduzca un email valido",
    "invalidDniMessage": "Introduzca una cédula valida",
    "allreadyExistMessage": "Ya existe una cuenta registrada con este número.",
    "userNotExistMessage": "No existe una cuenta registrada con este número.",
    "userDisabledMessage": "Cuenta deshabilitada",
    "addEmailMessage": "Especifique un email",
    "addAdress": "Especifique una dirrección",
    "addNationality": "Especifique su nacionalidad",
    "reportCreatedSuccessMessage": "Gracias por contribuir \ncreando este reporte",
    "reportCommentSuccessMessage": "Mensaje enviado exitosamente!",
    "typeReportMandatoryMessage": "Debe selecionar un tipo de denuncia.",
    "youMustEnterAtLastMessage": "Debe ingresar por lo menos ${amount}.",
    "youMustSelectMessage": "Debe selecionar ${value}",
    "youAreOnlyAllowedToEnterMessage": "Solo se puede introducir ${value}",
    "involvedMandatoryMessage": "Debe introducir al menos un Implicado",
    "maxFilesAndFileSizeMessage": "Puede adjuntar hasta (3) imágenes, con un peso máximo de (50 MB).",
    "deleteDataMessage": "¿Esta seguro que desea eliminar este dato?",
    "reportDescriptionHitMessage": "Describa los hecho que respaldan su denuncia, trate de ser claro y explícito, la información prestada a continuación es confidencial.",
    "saveDataMessage": "Se han actualizado los datos.",

    "menuHomeTile": "Inicio",

    "menuReportTitle": "Denuncias",
    "menuReportDescription": "Realizar las denuncias a través de la aplicación.",
    "menuReportGeneralReport": "Denuncias Generales",
    "menuReportMyReport": "Mis Denuncias",
    "menuReportAssistedReport": "Denuncias Asistidas",
    "menuReportStatistic": "Estadisticas",

    "newReportTitle": "Estas realizando una denuncia",
    "newReportSubTitle": "Continua paso a paso por el proceso de denuncia, puedes volver atrás a revisar lo que has hecho antes de confirmarla.",
    "newReportCancelMessage": "¿Está seguro que desea cancelar la creación de la denuncia?",

    "validProfileTitle": "Tienes que completar tu perfil",
    "validProfileSubtitle": "Accede para completar tu cuenta y poder crear tu denuncia.",


    "menuAboutUsTitle": "¿Quienes Somos?",
    "menuAboutUsDescription": "Información general de la defensoría ",

    "menuReportsAndStatisticsTitle": "Informes",
    "menuReportsAndStatisticsDescription": "Colaboración al desarrollo de diferentes proyectos de interés general.",
    
    "menuProfileTitle": "Perfil",

    "municipality" : "p r o v i n c i a",
    "textWelcome": "!Bienvenido¡ Aquí te conectas con tu comunidad y participas en su crecimiento",
    "pay": "PAGOS",
    "textPay" : "Realiza el pago de tus servicios de manera más rápida",
    "pickup": "RECOGIDA",
    "textPickup" : "Sigue la ruta del GPS del camión de recogida en tu sector",
    "report": "Reportes",
    "textReport" : "Reporta las incidencias de tu sector o lugares cercanos",

    "next": "CONTINUAR",
    "skip": "OMITIR",

    "loginWithoutQccount": "Acceder sin cuenta",
    "forgotPassword": "¿Olvidó la contraseña?",
    "login": "Iniciar Sesión",
    "loginAccountFacebook": "ACCEDE CON FACEBOOK",
    "register": "Registrarme",
    "dontHaveAccount": "¿No tienes una cuenta?",
    "password": "Contraseña",
    "email": "Email",
    "sendEmail": "ENVIAR CORREO",
    "messageForgotPass" : "Coloca tu correo aquí para que puedas recuperar tu contraseña",
    "usuario" : "Usuario",
    "crearCuenta" : "CREAR CUENTA",
    "cocle": "Coclé",
    "messageStart": "Crea una cuenta nueva o inicia sesión. ¡Empieza a interactuar con tu municipio!",
    "nextPage": "siguiente",
    "registerMe": "Regístrate",
    "codeSend": "Código \nenviado \npor SMS",
    "start": "Inicio",
    "welcome": "Bienvenido",
    "selectedMunicipality": "Selecciona tu Distrito",
    "connect": "Conectar",
    "menuReport": "Reportes",
    "menuRoute": "Recogidas",
    "menuPay": "Pagos",
    "menuTittle": "Menú",
    "myReports": "Mis reportes",
    "cercaMi": "Cerca de mí",
    "map": "Mapa",
    "all": "Todo",
    "validate": "Validar",
    "questionValidate": "¿Tu cuenta aún no esta validada?",
    "accessAccount":"Accede a tu correo y valida tu cuenta para poder crear un reporte",
    "questionValidateAccount":"¿Validaste tu cuenta?",
    "meesageValidate":"Cierra la sesión e inicia nuevamente para poder crear reportes.",
    "logout": "Cerrar sesión",
    "hello": "¡Hola!",
    "newReport": "Crear Reporte",
    "sector": "Sector",
    "ubicationPin": "Ubica el pin en el lugar exacto del reporte",
    "selectTypeReport": "Selecciona el tipo de incidente que deseas reportar",
    "completeData": "Por favor completar estos campos obligatorio para continuar",
    "one": "1",
    "two": "2",
    "tree": "3",
    "back": "atras",
    "nameStreet" : "Nombre de calle",
    "numberStreet" : "Número de calle",
    "neighborhood" : "Vecindario",
    "category": "Categoría",
    "categoryValid": "Seleccione una categoría válida antes de continuar",
    "sectorValid": "Seleccione una sector válido antes de continuar",
    "neighborhoodValid": "Seleccione una vecindario válido antes de continuar",
    "completeForm": "Complete el formulario antes de continuar",
    "titleReport": "Este reporte será enviado a la Alcaldia del Distrito Nacional y estará disponible en linea para el público en general, de acuerdo a nuestra ",
    "privacyPolitics" : "política de privacidad",
    "title": "Título",
    "exampleDescription" : "Ej. Un agujero grande en la Calle Tal donde los auts de caen. Tiene más de dos años.",
    "exampleTitle" : "Bache de 25 cm en la Calle Tal",
    "rule1": "Sea preciso y cortés al describir el problema",
    "rule2": "No identifique o acuse a otras personas",
    "ruleTree": "Indique el tiempo estimado que tiene el incidente",
    "ruleFour": "No incluya su información de contacto privada en la descripción",
    "files": "Subir foto",
    "reportFileNotFound": "Selecciona o tira una foto. Para mejor entendimiento incluya una toma close-up y una abierta.",
    "infoFile": "Evite fotografiar información personal y las placas de matrícula de los carros",
    "uptoPhoto": "Puedes agregar hasta 3 fotos",
    "takePhoto": "Tomar una nueva foto",
    "addPhotoExisting": "Añadir una foto existente",
    "questionPostYourName" : "¿Quieres publicar este reporte con tu nombre?",
    "finalize": "Finalizar",
    "photos": "Fotos",
    "summary": "Resumen",
    "infoCreateReport" : "Estaremos analizando el reporte y dándole seguimiento para notificarte cuando esté completado.",
    "reportNotFound": "No hay Reportes.",
    "follow": "Seguir",

    "status": "Estatus",
    "inProgress": "En Progreso",
    "close": "Cerrado",
    "Abierto": "Abierto",
    "distance": "Distancia",
    "userNotFoundTittle": "No hay ningún reporte cerca de ti",
    "userNotFoundMessage": "Por Favor inicia sesión o crea tu cuenta para que puedas ver y seguir los reportes cerca de ti.",
    "author": "Autor",
    "addPhoto": "Agregar foto",
    "comment": "Comentar",
    "messageAnonymous": "Mensaje Anónimo",
    "reportSingle": "Reporte",
    "empyteComment": "No hy ningún comentario",
    "messageComment" : "Sé el primero en comentar este reporte, queremos escuchar tus opiniones.",
    "followTrue": "Siguiendo",
    "tryAgain": "Intente nuevamente",
    "noConnectionMessage": "Al parecer no tiene conexión a internet, revise e intente nuevamente.",
    "posts": "Comunicados",
    "news": "Noticias",
    "training": "Capacitaciones",
    "announcement": "Convocatorias",
    "facilitador": "Falicitador",
    "duration": "Duración",
    "errollmentPeriod": "Período de inscripción",
    "schedule": "Horario",
    "cost": "Costo",
    "area": "Área",
    "courseType": "Tipo de curso",
    "announcementType": "Tipo de convocatoria",
    "getDirection": "Como llegar",
    "startDate": "Fecha de inicio",
    "endDate": "Fecha de finalizacíon"
}